pypegraph/__init__.py
pypegraph/action.py
pypegraph/connection.py
pypegraph/dag.py
pypegraph/node.py
pypegraph/node_factory.py
pypegraph/node_utils.py
pypegraph/utils.py
pypegraph-0.1.7.dist-info/LICENSE
pypegraph-0.1.7.dist-info/METADATA
pypegraph-0.1.7.dist-info/WHEEL
pypegraph-0.1.7.dist-info/top_level.txt
pypegraph-0.1.7.dist-info/RECORD
